{
  "schemaVersion": 1,
  "id": "waila",
  "version": "${version}",
  "depends": {
    "fishmodloader": ">=3.2.0",
    "many-lib": ">=2.2.0"
  },
  "recommends": {
    "emi": ">=1.0.4"
  },
  "environment": "*",
  "name": "Waila",
  "description": "All your data are belong to us. Fork from GTNH-Waila",
  "authors": [
    "ProfMobius",
    "Xy_Lose"
  ],
  "License": "MIT",
  "icon": "assets/minecraft/textures/hwite_icon.png",
  "contact": {
    "homepage": "https://www.mcmod.cn/class/15041.html",
    "issues": "https://github.com/ysesiq/HWITE/issues",
    "sources": "https://github.com/ysesiq/HWITE",
    "qqGroup": "661223990"
  },
  "entrypoints": {
    "main": [
      "mcp.mobius.waila.Waila"
    ]
  },
  "mixins": [
    "hwite.mixins.json"
  ],
  "accessWidener": "hwite.accesswidener",
  "custom": {
    "loom:injected_interfaces": {
    }
  }
}